leadlog/__init__.py
leadlog/__main__.py
leadlog/py.typed
leadlog-0.2.0.dist-info/LICENSE
leadlog-0.2.0.dist-info/METADATA
leadlog-0.2.0.dist-info/WHEEL
leadlog-0.2.0.dist-info/entry_points.txt
leadlog-0.2.0.dist-info/RECORD
