Metadata-Version: 2.1
Name: leadlog
Version: 0.2.0
Summary: LeadLog
Home-page: https://github.com/markm-io/leadlog
License: Apache-2.0
Author: Mark Moreno
Author-email: mark@securehst.com
Requires-Python: >=3.9,<4.0
Classifier: Development Status :: 1 - Planning
Classifier: License :: OSI Approved :: Apache Software License
Classifier: Programming Language :: Python :: 3
Classifier: Programming Language :: Python :: 3.9
Classifier: Programming Language :: Python :: 3.10
Classifier: Programming Language :: Python :: 3.11
Classifier: Programming Language :: Python :: 3.12
Classifier: Programming Language :: Python :: 3.13
Requires-Dist: click (>=8.0.1)
Project-URL: Changelog, https://github.com/markm-io/leadlog/releases
Project-URL: Documentation, https://leadlog.readthedocs.io
Project-URL: Repository, https://github.com/markm-io/leadlog
